cachier_python/Cachier.py
cachier_python/__init__.py
cachier_python-0.6.0.dist-info/LICENSE
cachier_python-0.6.0.dist-info/METADATA
cachier_python-0.6.0.dist-info/WHEEL
cachier_python-0.6.0.dist-info/top_level.txt
cachier_python-0.6.0.dist-info/RECORD
