Metadata-Version: 2.1
Name: cachier-python
Version: 0.6.0
Summary: A python wrapper package for connecting to a self-hosted cachier service
Home-page: https://github.com/apinanyogaratnam/cachier-python
Author: apinanyogaratnam
Author-email: apinanapinan@icloud.com
License: UNKNOWN
Platform: UNKNOWN
Classifier: Programming Language :: Python :: 3
Classifier: License :: OSI Approved :: MIT License
Classifier: Operating System :: OS Independent
Requires-Python: >=3.10.4
License-File: LICENSE
Requires-Dist: requests
Requires-Dist: cachier-common-library
